brave_search_python_client/__init__.py
brave_search_python_client/cli.py
brave_search_python_client/client.py
brave_search_python_client/constants.py
brave_search_python_client/requests.py
brave_search_python_client/responses/__init__.py
brave_search_python_client/responses/exceptions.py
brave_search_python_client/responses/image_search.py
brave_search_python_client/responses/news_search.py
brave_search_python_client/responses/video_search.py
brave_search_python_client/responses/web_search.py
brave_search_python_client/responses/mock_data/images.json
brave_search_python_client/responses/mock_data/news.json
brave_search_python_client/responses/mock_data/videos.json
brave_search_python_client/responses/mock_data/web.json
brave_search_python_client/utils/__init__.py
brave_search_python_client/utils/_cli.py
brave_search_python_client/utils/_console.py
brave_search_python_client/utils/_constants.py
brave_search_python_client/utils/_di.py
brave_search_python_client/utils/_health.py
brave_search_python_client/utils/_log.py
brave_search_python_client/utils/_process.py
brave_search_python_client/utils/_service.py
brave_search_python_client/utils/_settings.py
brave_search_python_client/utils/boot.py
brave_search_python_client/utils/.vendored/bottle.py
brave_search_python_client-0.4.27.dist-info/METADATA
brave_search_python_client-0.4.27.dist-info/WHEEL
brave_search_python_client-0.4.27.dist-info/entry_points.txt
brave_search_python_client-0.4.27.dist-info/licenses/LICENSE
brave_search_python_client-0.4.27.dist-info/RECORD
