Metadata-Version: 2.4
Name: brave-search-python-client
Version: 0.4.27
Summary: 🦁 Brave Search Python Client supporting Web, Image, News and Video search.
Project-URL: Homepage, https://brave-search-python-client.readthedocs.io/en/latest/
Project-URL: Documentation, https://brave-search-python-client.readthedocs.io/en/latest/
Project-URL: Source, https://github.com/helmut-hoffer-von-ankershoffen/brave-search-python-client
Project-URL: Changelog, https://github.com/helmut-hoffer-von-ankershoffen/brave-search-python-client/releases
Project-URL: Issues, https://github.com/helmut-hoffer-von-ankershoffen/brave-search-python-client/issues
Author-email: Helmut Hoffer von Ankershoffen <helmuthva@googlemail.com>
License: MIT License
License-File: LICENSE
Keywords: act,api,brave,brave-api,brave-search,brave-search-api,brave-search-python-client,bravesearch,bravesearchapi,codecov,copier,cyclonedx,detect-secrets,devcontainer,docker,git-cliff,jupyter,marimo,mypy,nox,oe-python-template,pip-audit,pip-licenses,pre-commit,pydantic,pypi,pytest,python,readthedocs,ruff,sonarcloud,sonarqube,sphinx,streamlit,typer,uv,web-search,websearch
Classifier: Development Status :: 2 - Pre-Alpha
Classifier: Framework :: AsyncIO
Classifier: Framework :: Pydantic
Classifier: Framework :: Pytest
Classifier: Intended Audience :: Developers
Classifier: Intended Audience :: End Users/Desktop
Classifier: License :: OSI Approved :: MIT License
Classifier: Natural Language :: English
Classifier: Operating System :: MacOS :: MacOS X
Classifier: Operating System :: Microsoft :: Windows
Classifier: Operating System :: POSIX :: Linux
Classifier: Programming Language :: Python
Classifier: Programming Language :: Python :: 3
Classifier: Programming Language :: Python :: 3.11
Classifier: Programming Language :: Python :: 3.12
Classifier: Programming Language :: Python :: 3.13
Classifier: Typing :: Typed
Requires-Python: <4.0,>=3.11
Requires-Dist: pydantic-settings>=2.9.1
Requires-Dist: tenacity>=9.1.2
Requires-Dist: typer>=0.15.1
Provides-Extra: examples
Requires-Dist: jinja2>=3.1.6; extra == 'examples'
Requires-Dist: jupyter>=1.1.1; extra == 'examples'
Requires-Dist: marimo>=0.13.1; extra == 'examples'
Requires-Dist: matplotlib>=3.10.1; extra == 'examples'
Requires-Dist: streamlit>=1.44.1; extra == 'examples'
